soiz/autoentry.py
soiz/modules/convert.py
soiz/modules/database.py
soiz/modules/dataframe.py
soiz/modules/file.py
soiz/modules/image.py
soiz/modules/llm.py
soiz/modules/ocr.py
soiz/modules/pdf.py
soiz/TTS/.models.json
soiz/TTS/__init__.py
soiz/TTS/api.py
soiz/TTS/bin/__init__.py
soiz/TTS/bin/collect_env_info.py
soiz/TTS/bin/compute_attention_masks.py
soiz/TTS/bin/compute_embeddings.py
soiz/TTS/bin/compute_statistics.py
soiz/TTS/bin/eval_encoder.py
soiz/TTS/bin/extract_tts_spectrograms.py
soiz/TTS/bin/find_unique_chars.py
soiz/TTS/bin/find_unique_phonemes.py
soiz/TTS/bin/remove_silence_using_vad.py
soiz/TTS/bin/resample.py
soiz/TTS/bin/synthesize.py
soiz/TTS/bin/train_encoder.py
soiz/TTS/bin/train_tts.py
soiz/TTS/bin/train_vocoder.py
soiz/TTS/bin/tune_wavegrad.py
soiz/TTS/config/__init__.py
soiz/TTS/config/shared_configs.py
soiz/TTS/configs/__init__.py
soiz/TTS/configs/align_tts_config.py
soiz/TTS/configs/bark_config.py
soiz/TTS/configs/delightful_tts_config.py
soiz/TTS/configs/fast_pitch_config.py
soiz/TTS/configs/fast_speech_config.py
soiz/TTS/configs/fastspeech2_config.py
soiz/TTS/configs/glow_tts_config.py
soiz/TTS/configs/neuralhmm_tts_config.py
soiz/TTS/configs/overflow_config.py
soiz/TTS/configs/shared_configs.py
soiz/TTS/configs/speedy_speech_config.py
soiz/TTS/configs/tacotron2_config.py
soiz/TTS/configs/tacotron_config.py
soiz/TTS/configs/tortoise_config.py
soiz/TTS/configs/vits_config.py
soiz/TTS/configs/xtts_config.py
soiz/TTS/datasets/__init__.py
soiz/TTS/datasets/dataset.py
soiz/TTS/datasets/formatters.py
soiz/TTS/demos/xtts_ft_demo/requirements.txt
soiz/TTS/demos/xtts_ft_demo/utils/formatter.py
soiz/TTS/demos/xtts_ft_demo/utils/gpt_train.py
soiz/TTS/demos/xtts_ft_demo/xtts_demo.py
soiz/TTS/encoder/__init__.py
soiz/TTS/encoder/configs/base_encoder_config.py
soiz/TTS/encoder/configs/emotion_encoder_config.py
soiz/TTS/encoder/configs/speaker_encoder_config.py
soiz/TTS/encoder/dataset.py
soiz/TTS/encoder/losses.py
soiz/TTS/encoder/models/base_encoder.py
soiz-0.1.8.dist-info/METADATA
soiz-0.1.8.dist-info/WHEEL
soiz-0.1.8.dist-info/RECORD
