Metadata-Version: 2.1
Name: soiz
Version: 0.1.8
Summary: soiz is awesome 🤘
Author: namtao
Author-email: vannam.pxb@gmail.com
Requires-Python: >=3.10,<4.0
Classifier: Programming Language :: Python :: 3
Classifier: Programming Language :: Python :: 3.10
Classifier: Programming Language :: Python :: 3.11
Classifier: Programming Language :: Python :: 3.12
Requires-Dist: colorlog (>=6.9.0,<7.0.0)
Requires-Dist: coqpit (>=0.0.17,<0.0.18)
Requires-Dist: dataframe-image (>=0.2.6,<0.3.0)
Requires-Dist: fastapi (>=0.115.6,<0.116.0)
Requires-Dist: google-generativeai (>=0.8.3,<0.9.0)
Requires-Dist: halo (>=0.0.31,<0.0.32)
Requires-Dist: img2pdf (>=0.5.1,<0.6.0)
Requires-Dist: ollama (>=0.4.4,<0.5.0)
Requires-Dist: opencv-python (>=4.10.0.84,<5.0.0.0)
Requires-Dist: pandas (>=2.2.3,<3.0.0)
Requires-Dist: pymupdf (>=1.25.0,<2.0.0)
Requires-Dist: pypdf2 (>=3.0.1,<4.0.0)
Requires-Dist: pypdfium2 (>=4.30.0,<5.0.0)
Requires-Dist: python-dotenv (>=1.0.1,<2.0.0)
Requires-Dist: python-multipart (>=0.0.19,<0.0.20)
Requires-Dist: surya-ocr (>=0.7.0,<0.8.0)
Requires-Dist: torch (>=2.5.1,<3.0.0)
Requires-Dist: torchaudio (>=2.5.1,<3.0.0)
Requires-Dist: torchvision (>=0.20.1,<0.21.0)
Requires-Dist: uvicorn (>=0.32.1,<0.33.0)
Requires-Dist: vinorm (>=2.0.7,<3.0.0)
Requires-Dist: watchdog (>=6.0.0,<7.0.0)
